lywsd03mmc/__init__.py
lywsd03mmc/lywsd03mmc.py
lywsd03mmc-0.1.0.data/scripts/lywsd03mmc
lywsd03mmc-0.1.0.data/scripts/lywsd03mmc2csv
lywsd03mmc-0.1.0.dist-info/LICENSE
lywsd03mmc-0.1.0.dist-info/METADATA
lywsd03mmc-0.1.0.dist-info/WHEEL
lywsd03mmc-0.1.0.dist-info/top_level.txt
lywsd03mmc-0.1.0.dist-info/RECORD
