Metadata-Version: 2.1
Name: lywsd03mmc
Version: 0.1.0
Summary: Xiaomi Mijia LYWSD03MMC sensor library
Home-page: https://github.com/uduncanu/lywsd03mmc
Author: Duncan Barclay
Author-email: duncan@duncanbarclay.uk
License: UNKNOWN
Platform: UNKNOWN
Classifier: Programming Language :: Python :: 3
Requires-Python: >=3.6
Requires-Dist: lywsd02 (==0.0.9)
